biohit_pipettor/__init__.py
biohit_pipettor/abstract_pipettor.py
biohit_pipettor/clr_wrapping/__init__.py
biohit_pipettor/clr_wrapping/clr_wrappers.py
biohit_pipettor/clr_wrapping/instrument.py
biohit_pipettor/clr_wrapping/instrument.pyi
biohit_pipettor/clr_wrapping/System.pyi
biohit_pipettor/errors.py
biohit_pipettor/include/__init__.py
biohit_pipettor/include/InstrumentLib.dll
biohit_pipettor/include/InstrumentLib.pdf
biohit_pipettor/include/InstrumentLib.xml
biohit_pipettor/pipettor.py
biohit_pipettor/pipettor_simulator.py
biohit_pipettor/py.typed
open_biohit-0.0.2.dist-info/LICENSE
open_biohit-0.0.2.dist-info/METADATA
open_biohit-0.0.2.dist-info/WHEEL
open_biohit-0.0.2.dist-info/RECORD
