Metadata-Version: 2.3
Name: open-biohit
Version: 0.0.2
Summary: Python interface to the InstrumentLib.dll provided by the device vendor
License: MIT
Author: Niklas Mertsch
Author-email: niklas.mertsch@stud.uni-goettingen.de
Requires-Python: >=3.9,<4.0
Classifier: License :: OSI Approved :: MIT License
Classifier: Programming Language :: Python :: 3
Classifier: Programming Language :: Python :: 3.9
Classifier: Programming Language :: Python :: 3.10
Classifier: Programming Language :: Python :: 3.11
Classifier: Programming Language :: Python :: 3.12
Classifier: Programming Language :: Python :: 3.13
Requires-Dist: pythonnet (>=3.0.3,<4.0.0)
